project_chooser/__init__.py
project_chooser/analysis/__init__.py
project_chooser/analysis/summariser.py
project_chooser/cli.py
project_chooser/config/__init__.py
project_chooser/config/settings.py
project_chooser/core/__init__.py
project_chooser/core/bayesian.py
project_chooser/core/clustering.py
project_chooser/core/niche_discovery.py
project_chooser/core/recommender.py
project_chooser/data/__init__.py
project_chooser/data/loader.py
project_chooser/data/models.py
project_chooser/data/validator.py
project_chooser/utils/__init__.py
project_chooser/utils/display.py
project_chooser/utils/io.py
project_chooser-1.0.0.dist-info/entry_points.txt
project_chooser-1.0.0.dist-info/LICENCE
project_chooser-1.0.0.dist-info/METADATA
project_chooser-1.0.0.dist-info/WHEEL
project_chooser-1.0.0.dist-info/RECORD
