Metadata-Version: 2.3
Name: project-chooser
Version: 1.0.0
Summary: Enhanced project recommendation system with advanced niche discovery features
License: MIT
Keywords: education,project,recommendation,academic,machine-learning,cli
Author: William Fayers
Author-email: william@fayers.com
Requires-Python: >=3.9,<4.0
Classifier: Development Status :: 4 - Beta
Classifier: Environment :: Console
Classifier: Intended Audience :: Education
Classifier: License :: OSI Approved :: MIT License
Classifier: Operating System :: OS Independent
Classifier: Programming Language :: Python :: 3
Classifier: Programming Language :: Python :: 3.9
Classifier: Programming Language :: Python :: 3.10
Classifier: Programming Language :: Python :: 3.11
Classifier: Programming Language :: Python :: 3.12
Classifier: Programming Language :: Python :: 3.13
Classifier: Topic :: Education
Classifier: Topic :: Scientific/Engineering :: Artificial Intelligence
Requires-Dist: numpy (>=1.24.0,<2.0.0)
Requires-Dist: pydantic (>=2.0.0,<3.0.0)
Requires-Dist: questionary (>=2.0.1,<3.0.0)
Requires-Dist: rich (>=13.0.0,<14.0.0)
Requires-Dist: typer[all] (>=0.9.0,<0.10.0)
Project-URL: Documentation, https://github.com/unkokaeru/project-chooser#readme
Project-URL: Homepage, https://github.com/unkokaeru/project-chooser
Project-URL: Repository, https://github.com/unkokaeru/project-chooser
